django_docxtpl/__init__.py
django_docxtpl/converters.py
django_docxtpl/mixins.py
django_docxtpl/py.typed
django_docxtpl/response.py
django_docxtpl/utils.py
django_docxtpl/views.py
django_docxtpl-0.9.0.dist-info/licenses/LICENSE
django_docxtpl-0.9.0.dist-info/WHEEL
django_docxtpl-0.9.0.dist-info/METADATA
django_docxtpl-0.9.0.dist-info/RECORD
