Metadata-Version: 2.4
Name: django-docxtpl
Version: 0.9.0
Summary: Django integration for docxtpl - generate documents from Word templates with multi-format export
Keywords: django,docx,template,word,pdf,document,docxtpl,report,reporting
Author: ctrl-alt-d
Requires-Python: >=3.10
Classifier: Development Status :: 3 - Alpha
Classifier: Environment :: Web Environment
Classifier: Framework :: Django
Classifier: Framework :: Django :: 4.2
Classifier: Framework :: Django :: 5.0
Classifier: Intended Audience :: Developers
Classifier: License :: OSI Approved :: MIT License
Classifier: Operating System :: OS Independent
Classifier: Programming Language :: Python :: 3
Classifier: Programming Language :: Python :: 3.10
Classifier: Programming Language :: Python :: 3.11
Classifier: Programming Language :: Python :: 3.12
Classifier: Topic :: Internet :: WWW/HTTP
Classifier: Topic :: Office/Business
License-File: LICENSE
Requires-Dist: django>=4.2
Requires-Dist: docxtpl>=0.16
Requires-Dist: pytest>=7.0 ; extra == "dev"
Requires-Dist: pytest-django>=4.5 ; extra == "dev"
Requires-Dist: ruff>=0.1 ; extra == "dev"
Requires-Dist: mypy>=1.0 ; extra == "dev"
Requires-Dist: django-stubs>=4.2 ; extra == "dev"
Project-URL: Homepage, https://github.com/ctrl-alt-d/django-docxtpl
Project-URL: Issues, https://github.com/ctrl-alt-d/django-docxtpl/issues
Project-URL: Repository, https://github.com/ctrl-alt-d/django-docxtpl
Provides-Extra: dev
